genpdf_butler/GenPDF.py
genpdf_butler/PatchTextColor.py
genpdf_butler/__init__.py
genpdf_butler/__main__.py
genpdf_butler-0.0.31.dist-info/METADATA
genpdf_butler-0.0.31.dist-info/WHEEL
genpdf_butler-0.0.31.dist-info/entry_points.txt
genpdf_butler-0.0.31.dist-info/RECORD
